ind_tools/__init__.py
ind_tools/IndTransformer.py
tti_dataset_tools/__init__.py
tti_dataset_tools/ColMapper.py
tti_dataset_tools/InfluenceAnalyzer.py
tti_dataset_tools/models/__init__.py
tti_dataset_tools/models/CrosswalkModel.py
tti_dataset_tools/patterns/__init__.py
tti_dataset_tools/patterns/RegularKnotsModel.py
tti_dataset_tools/TrackClass.py
tti_dataset_tools/TrackDirection.py
tti_dataset_tools/TrajectoryCleaner.py
tti_dataset_tools/TrajectoryMetaBuilder.py
tti_dataset_tools/TrajectoryProcessor.py
tti_dataset_tools/TrajectoryTransformer.py
tti_dataset_tools/TrajectoryUtils.py
tti_dataset_tools/TrajectoryVisualizer.py
tti_dataset_tools-0.1.11.dist-info/LICENSE
tti_dataset_tools-0.1.11.dist-info/METADATA
tti_dataset_tools-0.1.11.dist-info/WHEEL
tti_dataset_tools-0.1.11.dist-info/RECORD
